brainrot_id/__init__.py
brainrot_id/cli.py
brainrot_id/core.py
brainrot_id/data/components.json
brainrot_id/data/phrases.json
brainrot_id-0.1.4.dist-info/licenses/LICENSE
brainrot_id-0.1.4.dist-info/METADATA
brainrot_id-0.1.4.dist-info/WHEEL
brainrot_id-0.1.4.dist-info/entry_points.txt
brainrot_id-0.1.4.dist-info/top_level.txt
brainrot_id-0.1.4.dist-info/RECORD
