Metadata-Version: 2.4
Name: brainrot-id
Version: 0.1.4
Summary: Brain-melting ID generator for post-modern applications
Author: Nercy
Author-email: nercysvoboda@gmail.com
Project-URL: Homepage, https://github.com/n3rcy/brainrot-id
Project-URL: Bug Tracker, https://github.com/n3rcy/brainrot-id/issues
Classifier: Programming Language :: Python :: 3
Classifier: License :: OSI Approved :: MIT License
Classifier: Operating System :: OS Independent
Requires-Python: >=3.8
License-File: LICENSE
Requires-Dist: emoji>=2.0.0
Requires-Dist: cryptography>=3.4
Dynamic: author
Dynamic: author-email
Dynamic: classifier
Dynamic: description
Dynamic: description-content-type
Dynamic: license-file
Dynamic: project-url
Dynamic: requires-dist
Dynamic: requires-python
Dynamic: summary
